pypowsybl_grid2opbackend/__init__.py
pypowsybl_grid2opbackend/Backend/__init__.py
pypowsybl_grid2opbackend/Backend/network.py
pypowsybl_grid2opbackend/Backend/powsybl_backend.py
pypowsybl_grid2opbackend/basic_tests.py
pypowsybl_grid2opbackend/data_test/grid.json
pypowsybl_grid2opbackend/data_test/l2rpn_case14_sandbox_Pypowsybl/chronics/0000/load_p.csv.bz2
pypowsybl_grid2opbackend/data_test/l2rpn_case14_sandbox_Pypowsybl/chronics/0000/load_p_forecasted.csv.bz2
pypowsybl_grid2opbackend/data_test/l2rpn_case14_sandbox_Pypowsybl/chronics/0000/load_q.csv.bz2
pypowsybl_grid2opbackend/data_test/l2rpn_case14_sandbox_Pypowsybl/chronics/0000/load_q_forecasted.csv.bz2
pypowsybl_grid2opbackend/data_test/l2rpn_case14_sandbox_Pypowsybl/chronics/0000/prod_p.csv.bz2
pypowsybl_grid2opbackend/data_test/l2rpn_case14_sandbox_Pypowsybl/chronics/0000/prod_p_forecasted.csv.bz2
pypowsybl_grid2opbackend/data_test/l2rpn_case14_sandbox_Pypowsybl/chronics/0000/prod_v.csv.bz2
pypowsybl_grid2opbackend/data_test/l2rpn_case14_sandbox_Pypowsybl/chronics/0000/prod_v_forecasted.csv.bz2
pypowsybl_grid2opbackend/data_test/l2rpn_case14_sandbox_Pypowsybl/chronics/0000/start_datetime.info
pypowsybl_grid2opbackend/data_test/l2rpn_case14_sandbox_Pypowsybl/chronics/0000/time_interval.info
pypowsybl_grid2opbackend/data_test/l2rpn_case14_sandbox_Pypowsybl/chronics/0001/load_p.csv.bz2
pypowsybl_grid2opbackend/data_test/l2rpn_case14_sandbox_Pypowsybl/chronics/0001/load_p_forecasted.csv.bz2
pypowsybl_grid2opbackend/data_test/l2rpn_case14_sandbox_Pypowsybl/chronics/0001/load_q.csv.bz2
pypowsybl_grid2opbackend/data_test/l2rpn_case14_sandbox_Pypowsybl/chronics/0001/load_q_forecasted.csv.bz2
pypowsybl_grid2opbackend/data_test/l2rpn_case14_sandbox_Pypowsybl/chronics/0001/prod_p.csv.bz2
pypowsybl_grid2opbackend/data_test/l2rpn_case14_sandbox_Pypowsybl/chronics/0001/prod_p_forecasted.csv.bz2
pypowsybl_grid2opbackend/data_test/l2rpn_case14_sandbox_Pypowsybl/chronics/0001/prod_v.csv.bz2
pypowsybl_grid2opbackend-1.0.0.dist-info/LICENSE
pypowsybl_grid2opbackend-1.0.0.dist-info/METADATA
pypowsybl_grid2opbackend-1.0.0.dist-info/WHEEL
pypowsybl_grid2opbackend-1.0.0.dist-info/RECORD
