Metadata-Version: 2.1
Name: pypowsybl_grid2opbackend
Version: 1.0.0
Summary: 
Author: Rémi Tschupp
Author-email: remi.tschupp@artelyes.com
Requires-Python: >=3.9,<4.0
Classifier: Programming Language :: Python :: 3
Classifier: Programming Language :: Python :: 3.9
Classifier: Programming Language :: Python :: 3.10
Classifier: Programming Language :: Python :: 3.11
Classifier: Programming Language :: Python :: 3.12
Requires-Dist: grid2op (>=1.9.7,<2.0.0)
Requires-Dist: l2rpn-baselines (>=0.8.0,<0.9.0)
Requires-Dist: pandapower (>=2.13.1,<3.0.0)
Requires-Dist: pypowsybl (>=0.23.0.dev1,<0.24.0)
Requires-Dist: stable-baselines3 (>=2.1.0,<3.0.0)
Requires-Dist: urllib3 (>=1.26.0,<2.0.0)
